qcware_transpile/__init__.py
qcware_transpile/builder.py
qcware_transpile/circuits.py
qcware_transpile/dialects/__init__.py
qcware_transpile/dialects/braket/__init__.py
qcware_transpile/dialects/braket/braket_dialect.py
qcware_transpile/dialects/pyzx/__init__.py
qcware_transpile/dialects/pyzx/pyzx_dialect.py
qcware_transpile/dialects/qiskit/__init__.py
qcware_transpile/dialects/qiskit/qiskit_dialect.py
qcware_transpile/dialects/qsharp/__init__.py
qcware_transpile/dialects/qsharp/qsharp_dialect.py
qcware_transpile/dialects/quasar/__init__.py
qcware_transpile/dialects/quasar/quasar_dialect.py
qcware_transpile/exceptions.py
qcware_transpile/gates.py
qcware_transpile/helpers.py
qcware_transpile/instructions.py
qcware_transpile/matching.py
qcware_transpile/py.typed
qcware_transpile/serialization.py
qcware_transpile/translations/__init__.py
qcware_transpile/translations/braket/__init__.py
qcware_transpile/translations/braket/to_quasar/__init__.py
qcware_transpile/translations/pyzx/__init__.py
qcware_transpile/translations/pyzx/to_quasar/__init__.py
qcware_transpile/translations/qiskit/__init__.py
qcware_transpile/translations/qiskit/to_quasar/__init__.py
qcware_transpile/translations/quasar/__init__.py
qcware_transpile/translations/quasar/to_braket/__init__.py
qcware_transpile/translations/quasar/to_pyzx/__init__.py
qcware_transpile/translations/quasar/to_qiskit/__init__.py
qcware_transpile/translations/quasar/to_qsharp/__init__.py
qcware_transpile-0.1.1a21.dist-info/WHEEL
qcware_transpile-0.1.1a21.dist-info/METADATA
qcware_transpile-0.1.1a21.dist-info/RECORD
