Metadata-Version: 2.1
Name: qcware-transpile
Version: 0.1.1a21
Summary: A quantum circuit transpilation framework
Author: Vic Putz
Author-email: vic.putz@qcware.com
Requires-Python: >=3.8,<4.0
Classifier: Programming Language :: Python :: 3
Classifier: Programming Language :: Python :: 3.10
Classifier: Programming Language :: Python :: 3.8
Classifier: Programming Language :: Python :: 3.9
Provides-Extra: braket
Provides-Extra: pyzx
Provides-Extra: qcware-quasar
Provides-Extra: qiskit
Provides-Extra: qsharp
Requires-Dist: amazon-braket-sdk (>=1.15.0); extra == "braket"
Requires-Dist: attrs (>=21.2.0,<22.0.0)
Requires-Dist: icontract (>=2.6.0,<3.0.0)
Requires-Dist: parse (>=1.19.0,<2.0.0)
Requires-Dist: pyrsistent (>=0.18.0,<0.19.0)
Requires-Dist: pyzx (>=0.6.4,<0.7.0); extra == "pyzx"
Requires-Dist: qcware-quasar (>=1.0.6,<2.0.0); extra == "qcware-quasar"
Requires-Dist: qiskit-aer (>=0.10.0,<0.11.0); extra == "qiskit"
Requires-Dist: qsharp (>=0.15.2102,<0.16.0); extra == "qsharp"
Requires-Dist: toolz (>=0.11.2,<0.12.0)
